{
    "ui": "tui",
    "tasks": {
        "build": {
            "dependsOn": [
                "^build"
            ]
        },
        "lint": {
            "dependsOn": [
                "^lint"
            ]
        },
        "check-types": {
            "dependsOn": [
                "^check-types"
            ]
        },
        "dev": {
            "cache": false,
            "persistent": true
        },
        "clean": {
            "cache": false
        },
        "//#clean": {
            "cache": false
        }
    }
}